tasklit/__init__.py
tasklit/__main__.py
tasklit/app.py
tasklit/pages/__init__.py
tasklit/pages/homepage.py
tasklit/pages/layouts/__init__.py
tasklit/pages/layouts/homepage_explore_task.py
tasklit/pages/layouts/homepage_new_task.py
tasklit/settings/__init__.py
tasklit/settings/consts.py
tasklit/src/__init__.py
tasklit/src/utils/__init__.py
tasklit/src/utils/helpers.py
tasklit/src/utils/job_names.py
tasklit-0.0.4.dist-info/LICENSE
tasklit-0.0.4.dist-info/METADATA
tasklit-0.0.4.dist-info/WHEEL
tasklit-0.0.4.dist-info/entry_points.txt
tasklit-0.0.4.dist-info/top_level.txt
tasklit-0.0.4.dist-info/RECORD
